pytest_reporter_plus/__init__.py
pytest_reporter_plus/compute_filter_counts.py
pytest_reporter_plus/extract_link.py
pytest_reporter_plus/generate_html_report.py
pytest_reporter_plus/json_merge.py
pytest_reporter_plus/json_to_xml_converter.py
pytest_reporter_plus/plugin.py
pytest_reporter_plus/resolver_driver.py
pytest_reporter_plus/send_email_report.py
pytest_reporter_plus-0.3.6.dist-info/LICENSE
pytest_reporter_plus-0.3.6.dist-info/METADATA
pytest_reporter_plus-0.3.6.dist-info/WHEEL
pytest_reporter_plus-0.3.6.dist-info/entry_points.txt
pytest_reporter_plus-0.3.6.dist-info/RECORD
