Metadata-Version: 2.3
Name: pytest-reporter-plus
Version: 0.3.6
Summary: Lightweight enhanced HTML reporter for Pytest
License: MIT
Keywords: pytest,html-report,pytest-plugin,test-report,test-results,test-summary,reporting,python-testing,automated-testing,test-runner,report-generator,continuous-integration,ci-cd,pytest-html,pytest-report
Author: Emjey
Requires-Python: >=3.9,<4.0
Classifier: License :: OSI Approved :: MIT License
Classifier: Programming Language :: Python :: 3
Classifier: Programming Language :: Python :: 3.9
Classifier: Programming Language :: Python :: 3.10
Classifier: Programming Language :: Python :: 3.11
Classifier: Programming Language :: Python :: 3.12
Classifier: Programming Language :: Python :: 3.13
Requires-Dist: keyring (>=25.6.0,<26.0.0)
Requires-Dist: yagmail (>=0.15.293,<0.16.0)
Project-URL: Homepage, https://github.com/reporterplus/pytest-report-plus
Project-URL: Source, https://github.com/reporterplus/pytest-report-plus
Project-URL: Tracker, https://github.com/reporterplus/pytest-report-plus/issues
